<?xml version="1.0" encoding="utf-8"?>
<TextureAtlas imagePath="bf edgy.png">
	<!-- Created with Adobe Animate version 21.0.7.42652 -->
	<!-- http://www.adobe.com/products/animate.html -->
	<SubTexture name="BF NOTE DOWN edgy0000" x="0" y="0" width="374" height="357" frameX="-1" frameY="-5" frameWidth="375" frameHeight="362"/>
	<SubTexture name="BF NOTE DOWN edgy0001" x="0" y="0" width="374" height="357" frameX="-1" frameY="-5" frameWidth="375" frameHeight="362"/>
	<SubTexture name="BF NOTE DOWN edgy0002" x="382" y="0" width="373" height="362" frameX="0" frameY="0" frameWidth="375" frameHeight="362"/>
	<SubTexture name="BF NOTE DOWN edgy0003" x="382" y="0" width="373" height="362" frameX="0" frameY="0" frameWidth="375" frameHeight="362"/>
	<SubTexture name="BF NOTE DOWN edgy0004" x="382" y="0" width="373" height="362" frameX="0" frameY="0" frameWidth="375" frameHeight="362"/>
	<SubTexture name="BF NOTE DOWN edgy0005" x="382" y="0" width="373" height="362" frameX="0" frameY="0" frameWidth="375" frameHeight="362"/>
	<SubTexture name="BF NOTE DOWN edgy0006" x="382" y="0" width="373" height="362" frameX="0" frameY="0" frameWidth="375" frameHeight="362"/>
	<SubTexture name="BF NOTE DOWN edgy0007" x="382" y="0" width="373" height="362" frameX="0" frameY="0" frameWidth="375" frameHeight="362"/>
	<SubTexture name="BF NOTE DOWN edgy0008" x="382" y="0" width="373" height="362" frameX="0" frameY="0" frameWidth="375" frameHeight="362"/>
	<SubTexture name="BF NOTE DOWN edgy0009" x="382" y="0" width="373" height="362" frameX="0" frameY="0" frameWidth="375" frameHeight="362"/>
	<SubTexture name="BF NOTE DOWN edgy0010" x="382" y="0" width="373" height="362" frameX="0" frameY="0" frameWidth="375" frameHeight="362"/>
	<SubTexture name="BF NOTE DOWN edgy0011" x="382" y="0" width="373" height="362" frameX="0" frameY="0" frameWidth="375" frameHeight="362"/>
	<SubTexture name="BF NOTE DOWN edgy0012" x="382" y="0" width="373" height="362" frameX="0" frameY="0" frameWidth="375" frameHeight="362"/>
	<SubTexture name="BF NOTE DOWN edgy0013" x="382" y="0" width="373" height="362" frameX="0" frameY="0" frameWidth="375" frameHeight="362"/>
	<SubTexture name="BF NOTE DOWN edgy0014" x="382" y="0" width="373" height="362" frameX="0" frameY="0" frameWidth="375" frameHeight="362"/>
	<SubTexture name="BF NOTE DOWN edgy0015" x="382" y="0" width="373" height="362" frameX="0" frameY="0" frameWidth="375" frameHeight="362"/>
	<SubTexture name="BF NOTE DOWN edgy0016" x="382" y="0" width="373" height="362" frameX="0" frameY="0" frameWidth="375" frameHeight="362"/>
	<SubTexture name="BF NOTE DOWN edgy0017" x="382" y="0" width="373" height="362" frameX="0" frameY="0" frameWidth="375" frameHeight="362"/>
	<SubTexture name="BF NOTE DOWN edgy0018" x="382" y="0" width="373" height="362" frameX="0" frameY="0" frameWidth="375" frameHeight="362"/>
	<SubTexture name="BF NOTE DOWN edgy0019" x="382" y="0" width="373" height="362" frameX="0" frameY="0" frameWidth="375" frameHeight="362"/>
	<SubTexture name="BF NOTE DOWN edgy0020" x="382" y="0" width="373" height="362" frameX="0" frameY="0" frameWidth="375" frameHeight="362"/>
	<SubTexture name="BF NOTE DOWN edgy0021" x="382" y="0" width="373" height="362" frameX="0" frameY="0" frameWidth="375" frameHeight="362"/>
	<SubTexture name="BF NOTE DOWN edgy0022" x="382" y="0" width="373" height="362" frameX="0" frameY="0" frameWidth="375" frameHeight="362"/>
	<SubTexture name="BF NOTE DOWN edgy0023" x="382" y="0" width="373" height="362" frameX="0" frameY="0" frameWidth="375" frameHeight="362"/>
	<SubTexture name="BF NOTE DOWN edgy0024" x="382" y="0" width="373" height="362" frameX="0" frameY="0" frameWidth="375" frameHeight="362"/>
	<SubTexture name="BF NOTE DOWN edgy0025" x="382" y="0" width="373" height="362" frameX="0" frameY="0" frameWidth="375" frameHeight="362"/>
	<SubTexture name="BF NOTE DOWN edgy0026" x="382" y="0" width="373" height="362" frameX="0" frameY="0" frameWidth="375" frameHeight="362"/>
	<SubTexture name="BF NOTE DOWN edgy0027" x="382" y="0" width="373" height="362" frameX="0" frameY="0" frameWidth="375" frameHeight="362"/>
	<SubTexture name="BF NOTE DOWN edgy0028" x="382" y="0" width="373" height="362" frameX="0" frameY="0" frameWidth="375" frameHeight="362"/>
	<SubTexture name="BF NOTE DOWN edgy0029" x="382" y="0" width="373" height="362" frameX="0" frameY="0" frameWidth="375" frameHeight="362"/>
	<SubTexture name="BF NOTE LEFT edgy0000" x="763" y="0" width="383" height="406" frameX="0" frameY="0" frameWidth="385" frameHeight="406"/>
	<SubTexture name="BF NOTE LEFT edgy0001" x="763" y="0" width="383" height="406" frameX="0" frameY="0" frameWidth="385" frameHeight="406"/>
	<SubTexture name="BF NOTE LEFT edgy0002" x="1154" y="0" width="374" height="404" frameX="-11" frameY="-2" frameWidth="385" frameHeight="406"/>
	<SubTexture name="BF NOTE LEFT edgy0003" x="1154" y="0" width="374" height="404" frameX="-11" frameY="-2" frameWidth="385" frameHeight="406"/>
	<SubTexture name="BF NOTE LEFT edgy0004" x="1154" y="0" width="374" height="404" frameX="-11" frameY="-2" frameWidth="385" frameHeight="406"/>
	<SubTexture name="BF NOTE LEFT edgy0005" x="1154" y="0" width="374" height="404" frameX="-11" frameY="-2" frameWidth="385" frameHeight="406"/>
	<SubTexture name="BF NOTE LEFT edgy0006" x="1154" y="0" width="374" height="404" frameX="-11" frameY="-2" frameWidth="385" frameHeight="406"/>
	<SubTexture name="BF NOTE LEFT edgy0007" x="1154" y="0" width="374" height="404" frameX="-11" frameY="-2" frameWidth="385" frameHeight="406"/>
	<SubTexture name="BF NOTE LEFT edgy0008" x="1154" y="0" width="374" height="404" frameX="-11" frameY="-2" frameWidth="385" frameHeight="406"/>
	<SubTexture name="BF NOTE LEFT edgy0009" x="1154" y="0" width="374" height="404" frameX="-11" frameY="-2" frameWidth="385" frameHeight="406"/>
	<SubTexture name="BF NOTE LEFT edgy0010" x="1154" y="0" width="374" height="404" frameX="-11" frameY="-2" frameWidth="385" frameHeight="406"/>
	<SubTexture name="BF NOTE LEFT edgy0011" x="1154" y="0" width="374" height="404" frameX="-11" frameY="-2" frameWidth="385" frameHeight="406"/>
	<SubTexture name="BF NOTE LEFT edgy0012" x="1154" y="0" width="374" height="404" frameX="-11" frameY="-2" frameWidth="385" frameHeight="406"/>
	<SubTexture name="BF NOTE LEFT edgy0013" x="1154" y="0" width="374" height="404" frameX="-11" frameY="-2" frameWidth="385" frameHeight="406"/>
	<SubTexture name="BF NOTE LEFT edgy0014" x="1536" y="0" width="374" height="404" frameX="-11" frameY="-2" frameWidth="385" frameHeight="406"/>
	<SubTexture name="BF NOTE RIGHT edgy0000" x="0" y="414" width="408" height="405" frameX="-1" frameY="-2" frameWidth="409" frameHeight="407"/>
	<SubTexture name="BF NOTE RIGHT edgy0001" x="0" y="414" width="408" height="405" frameX="-1" frameY="-2" frameWidth="409" frameHeight="407"/>
	<SubTexture name="BF NOTE RIGHT edgy0002" x="416" y="414" width="408" height="407" frameX="0" frameY="0" frameWidth="409" frameHeight="407"/>
	<SubTexture name="BF NOTE RIGHT edgy0003" x="416" y="414" width="408" height="407" frameX="0" frameY="0" frameWidth="409" frameHeight="407"/>
	<SubTexture name="BF NOTE RIGHT edgy0004" x="416" y="414" width="408" height="407" frameX="0" frameY="0" frameWidth="409" frameHeight="407"/>
	<SubTexture name="BF NOTE RIGHT edgy0005" x="416" y="414" width="408" height="407" frameX="0" frameY="0" frameWidth="409" frameHeight="407"/>
	<SubTexture name="BF NOTE RIGHT edgy0006" x="416" y="414" width="408" height="407" frameX="0" frameY="0" frameWidth="409" frameHeight="407"/>
	<SubTexture name="BF NOTE RIGHT edgy0007" x="416" y="414" width="408" height="407" frameX="0" frameY="0" frameWidth="409" frameHeight="407"/>
	<SubTexture name="BF NOTE RIGHT edgy0008" x="416" y="414" width="408" height="407" frameX="0" frameY="0" frameWidth="409" frameHeight="407"/>
	<SubTexture name="BF NOTE RIGHT edgy0009" x="416" y="414" width="408" height="407" frameX="0" frameY="0" frameWidth="409" frameHeight="407"/>
	<SubTexture name="BF NOTE RIGHT edgy0010" x="416" y="414" width="408" height="407" frameX="0" frameY="0" frameWidth="409" frameHeight="407"/>
	<SubTexture name="BF NOTE RIGHT edgy0011" x="416" y="414" width="408" height="407" frameX="0" frameY="0" frameWidth="409" frameHeight="407"/>
	<SubTexture name="BF NOTE RIGHT edgy0012" x="416" y="414" width="408" height="407" frameX="0" frameY="0" frameWidth="409" frameHeight="407"/>
	<SubTexture name="BF NOTE RIGHT edgy0013" x="416" y="414" width="408" height="407" frameX="0" frameY="0" frameWidth="409" frameHeight="407"/>
	<SubTexture name="BF NOTE RIGHT edgy0014" x="416" y="414" width="408" height="407" frameX="0" frameY="0" frameWidth="409" frameHeight="407"/>
	<SubTexture name="BF NOTE RIGHT edgy0015" x="416" y="414" width="408" height="407" frameX="0" frameY="0" frameWidth="409" frameHeight="407"/>
	<SubTexture name="BF NOTE RIGHT edgy0016" x="416" y="414" width="408" height="407" frameX="0" frameY="0" frameWidth="409" frameHeight="407"/>
	<SubTexture name="BF NOTE RIGHT edgy0017" x="416" y="414" width="408" height="407" frameX="0" frameY="0" frameWidth="409" frameHeight="407"/>
	<SubTexture name="BF NOTE RIGHT edgy0018" x="416" y="414" width="408" height="407" frameX="0" frameY="0" frameWidth="409" frameHeight="407"/>
	<SubTexture name="BF NOTE RIGHT edgy0019" x="416" y="414" width="408" height="407" frameX="0" frameY="0" frameWidth="409" frameHeight="407"/>
	<SubTexture name="BF NOTE RIGHT edgy0020" x="416" y="414" width="408" height="407" frameX="0" frameY="0" frameWidth="409" frameHeight="407"/>
	<SubTexture name="BF NOTE RIGHT edgy0021" x="416" y="414" width="408" height="407" frameX="0" frameY="0" frameWidth="409" frameHeight="407"/>
	<SubTexture name="BF NOTE RIGHT edgy0022" x="416" y="414" width="408" height="407" frameX="0" frameY="0" frameWidth="409" frameHeight="407"/>
	<SubTexture name="BF NOTE RIGHT edgy0023" x="416" y="414" width="408" height="407" frameX="0" frameY="0" frameWidth="409" frameHeight="407"/>
	<SubTexture name="BF NOTE RIGHT edgy0024" x="416" y="414" width="408" height="407" frameX="0" frameY="0" frameWidth="409" frameHeight="407"/>
	<SubTexture name="BF NOTE RIGHT edgy0025" x="416" y="414" width="408" height="407" frameX="0" frameY="0" frameWidth="409" frameHeight="407"/>
	<SubTexture name="BF NOTE RIGHT edgy0026" x="416" y="414" width="408" height="407" frameX="0" frameY="0" frameWidth="409" frameHeight="407"/>
	<SubTexture name="BF NOTE RIGHT edgy0027" x="416" y="414" width="408" height="407" frameX="0" frameY="0" frameWidth="409" frameHeight="407"/>
	<SubTexture name="BF NOTE RIGHT edgy0028" x="416" y="414" width="408" height="407" frameX="0" frameY="0" frameWidth="409" frameHeight="407"/>
	<SubTexture name="BF NOTE RIGHT edgy0029" x="416" y="414" width="408" height="407" frameX="0" frameY="0" frameWidth="409" frameHeight="407"/>
	<SubTexture name="BF NOTE RIGHT edgy0030" x="416" y="414" width="408" height="407" frameX="0" frameY="0" frameWidth="409" frameHeight="407"/>
	<SubTexture name="BF NOTE RIGHT edgy0031" x="416" y="414" width="408" height="407" frameX="0" frameY="0" frameWidth="409" frameHeight="407"/>
	<SubTexture name="BF NOTE RIGHT edgy0032" x="416" y="414" width="408" height="407" frameX="0" frameY="0" frameWidth="409" frameHeight="407"/>
	<SubTexture name="BF NOTE RIGHT edgy0033" x="416" y="414" width="408" height="407" frameX="0" frameY="0" frameWidth="409" frameHeight="407"/>
	<SubTexture name="BF NOTE RIGHT edgy0034" x="416" y="414" width="408" height="407" frameX="0" frameY="0" frameWidth="409" frameHeight="407"/>
	<SubTexture name="BF NOTE RIGHT edgy0035" x="416" y="414" width="408" height="407" frameX="0" frameY="0" frameWidth="409" frameHeight="407"/>
	<SubTexture name="BF NOTE RIGHT edgy0036" x="416" y="414" width="408" height="407" frameX="0" frameY="0" frameWidth="409" frameHeight="407"/>
	<SubTexture name="BF NOTE RIGHT edgy0037" x="416" y="414" width="408" height="407" frameX="0" frameY="0" frameWidth="409" frameHeight="407"/>
	<SubTexture name="BF NOTE RIGHT edgy0038" x="416" y="414" width="408" height="407" frameX="0" frameY="0" frameWidth="409" frameHeight="407"/>
	<SubTexture name="BF NOTE RIGHT edgy0039" x="416" y="414" width="408" height="407" frameX="0" frameY="0" frameWidth="409" frameHeight="407"/>
	<SubTexture name="BF NOTE RIGHT edgy0040" x="416" y="414" width="408" height="407" frameX="0" frameY="0" frameWidth="409" frameHeight="407"/>
	<SubTexture name="BF NOTE RIGHT edgy0041" x="416" y="414" width="408" height="407" frameX="0" frameY="0" frameWidth="409" frameHeight="407"/>
	<SubTexture name="BF NOTE RIGHT edgy0042" x="416" y="414" width="408" height="407" frameX="0" frameY="0" frameWidth="409" frameHeight="407"/>
	<SubTexture name="BF NOTE RIGHT edgy0043" x="416" y="414" width="408" height="407" frameX="0" frameY="0" frameWidth="409" frameHeight="407"/>
	<SubTexture name="BF NOTE RIGHT edgy0044" x="416" y="414" width="408" height="407" frameX="0" frameY="0" frameWidth="409" frameHeight="407"/>
	<SubTexture name="BF NOTE RIGHT edgy0045" x="416" y="414" width="408" height="407" frameX="0" frameY="0" frameWidth="409" frameHeight="407"/>
	<SubTexture name="BF NOTE RIGHT edgy0046" x="416" y="414" width="408" height="407" frameX="0" frameY="0" frameWidth="409" frameHeight="407"/>
	<SubTexture name="BF NOTE RIGHT edgy0047" x="416" y="414" width="408" height="407" frameX="0" frameY="0" frameWidth="409" frameHeight="407"/>
	<SubTexture name="BF NOTE RIGHT edgy0048" x="416" y="414" width="408" height="407" frameX="0" frameY="0" frameWidth="409" frameHeight="407"/>
	<SubTexture name="BF NOTE RIGHT edgy0049" x="416" y="414" width="408" height="407" frameX="0" frameY="0" frameWidth="409" frameHeight="407"/>
	<SubTexture name="BF NOTE RIGHT edgy0050" x="416" y="414" width="408" height="407" frameX="0" frameY="0" frameWidth="409" frameHeight="407"/>
	<SubTexture name="BF NOTE RIGHT edgy0051" x="416" y="414" width="408" height="407" frameX="0" frameY="0" frameWidth="409" frameHeight="407"/>
	<SubTexture name="BF NOTE RIGHT edgy0052" x="416" y="414" width="408" height="407" frameX="0" frameY="0" frameWidth="409" frameHeight="407"/>
	<SubTexture name="BF NOTE RIGHT edgy0053" x="416" y="414" width="408" height="407" frameX="0" frameY="0" frameWidth="409" frameHeight="407"/>
	<SubTexture name="BF NOTE RIGHT edgy0054" x="416" y="414" width="408" height="407" frameX="0" frameY="0" frameWidth="409" frameHeight="407"/>
	<SubTexture name="BF NOTE RIGHT edgy0055" x="416" y="414" width="408" height="407" frameX="0" frameY="0" frameWidth="409" frameHeight="407"/>
	<SubTexture name="BF NOTE RIGHT edgy0056" x="416" y="414" width="408" height="407" frameX="0" frameY="0" frameWidth="409" frameHeight="407"/>
	<SubTexture name="BF NOTE RIGHT edgy0057" x="416" y="414" width="408" height="407" frameX="0" frameY="0" frameWidth="409" frameHeight="407"/>
	<SubTexture name="BF NOTE RIGHT edgy0058" x="416" y="414" width="408" height="407" frameX="0" frameY="0" frameWidth="409" frameHeight="407"/>
	<SubTexture name="BF NOTE RIGHT edgy0059" x="416" y="414" width="408" height="407" frameX="0" frameY="0" frameWidth="409" frameHeight="407"/>
	<SubTexture name="BF NOTE RIGHT edgy0060" x="416" y="414" width="408" height="407" frameX="0" frameY="0" frameWidth="409" frameHeight="407"/>
	<SubTexture name="BF NOTE RIGHT edgy0061" x="416" y="414" width="408" height="407" frameX="0" frameY="0" frameWidth="409" frameHeight="407"/>
	<SubTexture name="BF NOTE UP edgy0000" x="832" y="414" width="369" height="446" frameX="-5" frameY="0" frameWidth="376" frameHeight="446"/>
	<SubTexture name="BF NOTE UP edgy0001" x="832" y="414" width="369" height="446" frameX="-5" frameY="0" frameWidth="376" frameHeight="446"/>
	<SubTexture name="BF NOTE UP edgy0002" x="1209" y="414" width="376" height="441" frameX="0" frameY="-5" frameWidth="376" frameHeight="446"/>
	<SubTexture name="BF NOTE UP edgy0003" x="1209" y="414" width="376" height="441" frameX="0" frameY="-5" frameWidth="376" frameHeight="446"/>
	<SubTexture name="BF NOTE UP edgy0004" x="1209" y="414" width="376" height="441" frameX="0" frameY="-5" frameWidth="376" frameHeight="446"/>
	<SubTexture name="BF NOTE UP edgy0005" x="1209" y="414" width="376" height="441" frameX="0" frameY="-5" frameWidth="376" frameHeight="446"/>
	<SubTexture name="BF NOTE UP edgy0006" x="1209" y="414" width="376" height="441" frameX="0" frameY="-5" frameWidth="376" frameHeight="446"/>
	<SubTexture name="BF NOTE UP edgy0007" x="1209" y="414" width="376" height="441" frameX="0" frameY="-5" frameWidth="376" frameHeight="446"/>
	<SubTexture name="BF NOTE UP edgy0008" x="1209" y="414" width="376" height="441" frameX="0" frameY="-5" frameWidth="376" frameHeight="446"/>
	<SubTexture name="BF NOTE UP edgy0009" x="1209" y="414" width="376" height="441" frameX="0" frameY="-5" frameWidth="376" frameHeight="446"/>
	<SubTexture name="BF NOTE UP edgy0010" x="1209" y="414" width="376" height="441" frameX="0" frameY="-5" frameWidth="376" frameHeight="446"/>
	<SubTexture name="BF NOTE UP edgy0011" x="1209" y="414" width="376" height="441" frameX="0" frameY="-5" frameWidth="376" frameHeight="446"/>
	<SubTexture name="BF NOTE UP edgy0012" x="1209" y="414" width="376" height="441" frameX="0" frameY="-5" frameWidth="376" frameHeight="446"/>
	<SubTexture name="BF NOTE UP edgy0013" x="1209" y="414" width="376" height="441" frameX="0" frameY="-5" frameWidth="376" frameHeight="446"/>
	<SubTexture name="BF NOTE UP edgy0014" x="1209" y="414" width="376" height="441" frameX="0" frameY="-5" frameWidth="376" frameHeight="446"/>
	<SubTexture name="BF idle dance edgy0000" x="1593" y="414" width="406" height="392" frameX="-1" frameY="-20" frameWidth="411" frameHeight="412"/>
	<SubTexture name="BF idle dance edgy0001" x="1593" y="414" width="406" height="392" frameX="-1" frameY="-20" frameWidth="411" frameHeight="412"/>
	<SubTexture name="BF idle dance edgy0002" x="0" y="868" width="408" height="393" frameX="0" frameY="-19" frameWidth="411" frameHeight="412"/>
	<SubTexture name="BF idle dance edgy0003" x="0" y="868" width="408" height="393" frameX="0" frameY="-19" frameWidth="411" frameHeight="412"/>
	<SubTexture name="BF idle dance edgy0004" x="416" y="868" width="405" height="398" frameX="-3" frameY="-14" frameWidth="411" frameHeight="412"/>
	<SubTexture name="BF idle dance edgy0005" x="416" y="868" width="405" height="398" frameX="-3" frameY="-14" frameWidth="411" frameHeight="412"/>
	<SubTexture name="BF idle dance edgy0006" x="829" y="868" width="410" height="411" frameX="-1" frameY="-1" frameWidth="411" frameHeight="412"/>
	<SubTexture name="BF idle dance edgy0007" x="829" y="868" width="410" height="411" frameX="-1" frameY="-1" frameWidth="411" frameHeight="412"/>
	<SubTexture name="BF idle dance edgy0008" x="1247" y="868" width="408" height="412" frameX="-2" frameY="0" frameWidth="411" frameHeight="412"/>
	<SubTexture name="BF idle dance edgy0009" x="1247" y="868" width="408" height="412" frameX="-2" frameY="0" frameWidth="411" frameHeight="412"/>
	<SubTexture name="BF idle dance edgy0010" x="1247" y="868" width="408" height="412" frameX="-2" frameY="0" frameWidth="411" frameHeight="412"/>
	<SubTexture name="BF idle dance edgy0011" x="1247" y="868" width="408" height="412" frameX="-2" frameY="0" frameWidth="411" frameHeight="412"/>
	<SubTexture name="BF idle dance edgy0012" x="1247" y="868" width="408" height="412" frameX="-2" frameY="0" frameWidth="411" frameHeight="412"/>
	<SubTexture name="BF idle dance edgy0013" x="1247" y="868" width="408" height="412" frameX="-2" frameY="0" frameWidth="411" frameHeight="412"/>
	<SubTexture name="BF idle dance edgy0014" x="1247" y="868" width="408" height="412" frameX="-2" frameY="0" frameWidth="411" frameHeight="412"/>
	<SubTexture name="BF idle dance edgy0015" x="1247" y="868" width="408" height="412" frameX="-2" frameY="0" frameWidth="411" frameHeight="412"/>
	<SubTexture name="BF idle dance edgy0016" x="1247" y="868" width="408" height="412" frameX="-2" frameY="0" frameWidth="411" frameHeight="412"/>
	<SubTexture name="BF idle dance edgy0017" x="1247" y="868" width="408" height="412" frameX="-2" frameY="0" frameWidth="411" frameHeight="412"/>
	<SubTexture name="BF idle dance edgy0018" x="1247" y="868" width="408" height="412" frameX="-2" frameY="0" frameWidth="411" frameHeight="412"/>
	<SubTexture name="BF idle dance edgy0019" x="1247" y="868" width="408" height="412" frameX="-2" frameY="0" frameWidth="411" frameHeight="412"/>
	<SubTexture name="BF idle dance edgy0020" x="1247" y="868" width="408" height="412" frameX="-2" frameY="0" frameWidth="411" frameHeight="412"/>
	<SubTexture name="BF idle dance edgy0021" x="1247" y="868" width="408" height="412" frameX="-2" frameY="0" frameWidth="411" frameHeight="412"/>
	<SubTexture name="BF idle dance edgy0022" x="1247" y="868" width="408" height="412" frameX="-2" frameY="0" frameWidth="411" frameHeight="412"/>
	<SubTexture name="BF idle dance edgy0023" x="1247" y="868" width="408" height="412" frameX="-2" frameY="0" frameWidth="411" frameHeight="412"/>
</TextureAtlas>
